{
   "init": {
         "ui": "Well, according to the judge, this will be your life for the next six years.."
    },
	"hero" : {
			"name" : "Tyler",
			"cols" : 4,
			"rows" : 4,
			"width" : 30,
			"height" : 20,
			"x" : 2,
			"y" : 13,
			"direction" : 1
    },
    "ai": [
         {
			"name" : "Daniel",
			"cols" : 4,
			"rows" : 4,
			"width" : 30,
			"height" : 46,
			"x" : 7,
			"y" : 11,
			"direction" : 1,
                    "action" : [
                                        "Daniel:\nDon't just stand here. The warden wants to talk to you.",
                                        "Daniel:\nIt's just me you idiot."
                                ]
         },
         {
			"name" : "Daniel",
			"cols" : 4,
			"rows" : 4,
			"width" : 30,
			"height" : 46,
			"x" : 12,
			"y" : 20,
			"direction" : 2,
                    "action" : [
                                        "Marcus:\nWhat are you looking at?"
                                ]
         },
         {
			"name" : "Daniel",
			"cols" : 4,
			"rows" : 4,
			"width" : 30,
			"height" : 46,
			"x" : 1,
			"y" : 4,
			"direction" : 3,
                    "action" : [
                                        "Steve:\nMan, I could go for some Wendy's right about now."
                                ]
         },
         {
			"name" : "Daniel",
			"cols" : 4,
			"rows" : 4,
			"width" : 30,
			"height" : 46,
			"x" : 16,
			"y" : 4,
			"direction" : 4,
                    "action" : [
                                        "Jose:\nAndate che! No te conoczo."
                                ]
         }
    ],
    "hot-spot" : [
        
    ]
}